{
  "enviroment1": {
  "Url": "https://encrypted-tbn0.gstatic.com/images?q=tbn%3AANd9GcQFpKfEyboRS1BwhLP15fvIPGgeY6GAFqdTv4LsqpwqQbBwzbcy&usqp=CAU",
  "Location": "Egypt - Red Sea",
  "TimeStamp": "6 / 10 / 84",
  "Latitude": "26.8206° N",
  "Longitude": "30.8025° E",
  "Temperature": "22° C",
  "Depth": "1,200 ft",
  "Current": "Southern",
  "Pressure": "37.2848 atm",
  "uid":"I58sAutxprZjeysPiZDoutmqXVn1"
  },
  "environment2": {
  "Url": "https://whalesunderwater.com/wp-content/uploads/2019/12/20191109_0204.jpg",
  "Location": "New Guinea - Pacific Ocean",
  "TimeStamp": "4 / 15 / 84",
  "Latitude": "06.3150° S",
  "Longitude": "143.955 E",
  "Temperature": "28° C",
  "Depth": "55 ft",
  "Current": "Eastward Surface",
  "Pressure": "2.66305 atm",
  "uid": "KcyQzlu4ARWQFneHHXl1pwBXXth1"
  },
  "environment3": {
  "Url": "https://encrypted-tbn0.gstatic.com/images?q=tbn%3AANd9GcTDCgG4BVrcVr6gytmbWAfGTQ_Eyzl53ZrxdRN70fnMj7SZo_3_&usqp=CAU",
  "Location": "Polynesia - Atlantic Ocean",
  "TimeStamp": "4 / 13 / 83",
  "Latitude": "15.000° S",
  "Longitude": "12.9° E",
  "Temperature": "23° C",
  "Depth": "440 ft",
  "Current": "Westward",
  "Pressure": "14.3044 atm",
  "uid":"l6asVxZPnKTVlsKUlJBF16lY64c2"
  },
  "environment4": {
    "Url": "https://cdn.theculturetrip.com/wp-content/uploads/2018/10/at-gulen-dive-resort-youll-get-the-chance-to-explore-may-shipwrecks.jpg",
    "Location": "Bering Strait",
    "TimeStamp": "9 / 15 / 84",
    "Latitude": "10.3150° S",
    "Longitude": "13.955 E",
    "Temperature": "29° C",
    "Depth": "550 ft",
    "Current": "Northern Surface",
    "Pressure": "7.66305 atm",
    "uid": "llppB0BJWBZ3Kc4kQSeLZlDgnfb2"
    },
    "environment5": {
      "Url": "https://images.pexels.com/photos/3395879/pexels-photo-3395879.jpeg?auto=compress&cs=tinysrgb&dpr=1&w=500",
      "Location": "Bermuda",
      "TimeStamp": "9 / 5 / 88",
      "Latitude": "16.3150° S",
      "Longitude": "42.565 E",
      "Temperature": "33° C",
      "Depth": "1,000 ft",
      "Current": "South Pacific",
      "Pressure": "2.95205 atm",
      "uid": "llppB0BJWBZ3Kc4kQSeLZlDgnfb2"
      },
      "environment6": {
        "Url": "https://images.pexels.com/photos/2690764/pexels-photo-2690764.jpeg?auto=compress&cs=tinysrgb&dpr=3&h=750&w=1260",
        "Location": "Canary Islands",
        "TimeStamp": "12 / 1 / 92",
        "Latitude": "20.3150° S",
        "Longitude": "81.955 E",
        "Temperature": "25° C",
        "Depth": "692 ft",
        "Current": "GulStream",
        "Pressure": "1.8305 atm",
        "uid": "l6asVxZPnKTVlsKUlJBF16lY64c2"
        },
        "environment7": {
          "Url": "https://images.pexels.com/photos/3410956/pexels-photo-3410956.jpeg?auto=compress&cs=tinysrgb&dpr=1&w=500",
          "Location": "",
          "TimeStamp": "4 / 15 / 84",
          "Latitude": "35.3150° S",
          "Longitude": "120.955 E",
          "Temperature": "28° C",
          "Depth": "895 ft",
          "Current": "South Indian",
          "Pressure": "1.985305 atm",
          "uid": "I58sAutxprZjeysPiZDoutmqXVn1"
          }
  }
